<dataStore>
  <id>DataStoreInfoImpl-1b83c0bb:187002cf1d4:-7fa9</id>
  <name>hex350_grid_no2_2019</name>
  <description>hex350_grid_no2_2019</description>
  <type>GeoPackage</type>
  <enabled>true</enabled>
  <workspace>
    <id>WorkspaceInfoImpl-1b83c0bb:187002cf1d4:-7fe4</id>
  </workspace>
  <connectionParameters>
    <entry key="fetch size">1000</entry>
    <entry key="Expose primary keys">false</entry>
    <entry key="Batch insert size">1</entry>
    <entry key="database">file:///home/tomcat/ec_data/geopackage/hex350_grid_no2_2019.gpkg</entry>
    <entry key="read_only">false</entry>
    <entry key="dbtype">geopkg</entry>
    <entry key="namespace">camb</entry>
  </connectionParameters>
  <__default>false</__default>
  <dateCreated>2023-03-21 08:18:46.47 UTC</dateCreated>
  <disableOnConnFailure>false</disableOnConnFailure>
</dataStore>